LICENSE
MANIFEST.in
README.rst
setup.py
argument/__init__.py
argument/main.py
argument/version.py
argument.egg-info/PKG-INFO
argument.egg-info/SOURCES.txt
argument.egg-info/dependency_links.txt
argument.egg-info/top_level.txt