Metadata-Version: 1.0
Name: argument
Version: 1.4.0
Summary: Command line argument parsing library for python
Home-page: https://github.com/oskarnyqvist/arguments
Author: oskarnyqvist
Author-email: oskarnyqvist@gmail.com
License: The MIT License (MIT)
